LICENSE
django_rester/__init__.py
django_rester/client.py
django_rester/config.py
django_rester/decorators.py
django_rester/exceptions.py
django_rester/fields.py
django_rester/permission.py
django_rester/settings.py
django_rester/singleton.py
django_rester/status.py
django_rester/views.py
django_rester/rester_jwt/__init__.py
django_rester/rester_jwt/auth.py
django_rester/rester_jwt/settings.py
django_rester-0.0.6.36.dist-info/LICENSE
django_rester-0.0.6.36.dist-info/METADATA
django_rester-0.0.6.36.dist-info/WHEEL
django_rester-0.0.6.36.dist-info/top_level.txt
django_rester-0.0.6.36.dist-info/RECORD
