Metadata-Version: 2.1
Name: django-rester
Version: 0.0.6.36
Summary: Django REST API build helper
Home-page: http://lexycore.github.io/django-rester
Author: Sergei Kovalev
Author-email: zili.tnd@gmail.com
License: MIT
Download-URL: https://github.com/lexycore/django-rester.git
Keywords: development,API
Platform: UNKNOWN
Classifier: Development Status :: 5 - Production/Stable
Classifier: Environment :: Console
Classifier: Intended Audience :: Developers
Classifier: Topic :: Software Development :: Build Tools
Classifier: License :: OSI Approved :: MIT License
Classifier: Natural Language :: English
Classifier: Programming Language :: Python :: 3
Classifier: Programming Language :: Python :: 3.1
Classifier: Programming Language :: Python :: 3.2
Classifier: Programming Language :: Python :: 3.3
Classifier: Programming Language :: Python :: 3.4
Classifier: Programming Language :: Python :: 3.5
Classifier: Programming Language :: Python :: 3.6
Requires-Dist: django
Requires-Dist: pyjwt
Requires-Dist: django-rediser
